seedtools/.env
seedtools/__init__.py
seedtools/all_files_.py
seedtools/data_path_settings.py
seedtools/mini_utils.py
seedtools/seed_file.py
seedtools/test.py
seedtools-0.2.dist-info/METADATA
seedtools-0.2.dist-info/WHEEL
seedtools-0.2.dist-info/top_level.txt
seedtools-0.2.dist-info/RECORD
