Metadata-Version: 2.1
Name: seedtools
Version: 0.2
Summary: A lightweight toolkit for loading and managing versioned seed datasets in Python.
Author: Rashesh
Author-email: rashesh369@gmail.com
Requires-Dist: python-dotenv
